bb_integrations_lib/__init__.py
bb_integrations_lib/converters/__init__.py
bb_integrations_lib/gravitate/__init__.py
bb_integrations_lib/gravitate/base_api.py
bb_integrations_lib/gravitate/model.py
bb_integrations_lib/gravitate/pe_api.py
bb_integrations_lib/gravitate/rita_api.py
bb_integrations_lib/gravitate/sd_api.py
bb_integrations_lib/gravitate/testing/TTE/sd/models.py
bb_integrations_lib/gravitate/testing/TTE/sd/tests/test_models.py
bb_integrations_lib/gravitate/testing/__init__.py
bb_integrations_lib/gravitate/testing/builder.py
bb_integrations_lib/gravitate/testing/openapi.py
bb_integrations_lib/gravitate/testing/util.py
bb_integrations_lib/mappers/__init__.py
bb_integrations_lib/mappers/prices/__init__.py
bb_integrations_lib/mappers/prices/model.py
bb_integrations_lib/mappers/prices/price_mapper.py
bb_integrations_lib/mappers/prices/protocol.py
bb_integrations_lib/mappers/prices/util.py
bb_integrations_lib/mappers/rita_mapper.py
bb_integrations_lib/models/__init__.py
bb_integrations_lib/models/dtn_supplier_invoice.py
bb_integrations_lib/models/enums.py
bb_integrations_lib/models/pipeline_structs.py
bb_integrations_lib/models/probe/probe_event.py
bb_integrations_lib/models/probe/request_data.py
bb_integrations_lib/models/probe/resume_token.py
bb_integrations_lib/models/rita/audit.py
bb_integrations_lib/models/rita/auth.py
bb_integrations_lib/models/rita/bucket.py
bb_integrations_lib/models/rita/config.py
bb_integrations_lib/models/rita/constants.py
bb_integrations_lib/models/rita/crossroads_entities.py
bb_integrations_lib/models/rita/crossroads_mapping.py
bb_integrations_lib/models/rita/crossroads_monitoring.py
bb_integrations_lib/models/rita/crossroads_network.py
bb_integrations_lib/models/rita/crossroads_rules.py
bb_integrations_lib/models/rita/email.py
bb_integrations_lib/models/rita/issue.py
bb_integrations_lib/models/rita/mapping.py
bb_integrations_lib/models/rita/probe.py
bb_integrations_lib/models/rita/reference_data.py
bb_integrations_library-3.0.33.1.dist-info/WHEEL
bb_integrations_library-3.0.33.1.dist-info/METADATA
bb_integrations_library-3.0.33.1.dist-info/RECORD
